ankiapp_easy_deck/__init__.py
ankiapp_easy_deck/__main__.py
ankiapp_easy_deck/drafts/card.txt
ankiapp_easy_deck/drafts/deck.txt
ankiapp_easy_deck-0.1.3.dist-info/LICENSE.txt
ankiapp_easy_deck-0.1.3.dist-info/METADATA
ankiapp_easy_deck-0.1.3.dist-info/WHEEL
ankiapp_easy_deck-0.1.3.dist-info/top_level.txt
ankiapp_easy_deck-0.1.3.dist-info/RECORD
