Metadata-Version: 2.1
Name: ankiapp_easy_deck
Version: 0.1.3
Summary: Easy way to make an AnkiApp deck.
Author-email: Johannes <johannes-programming@posteo.org>
License: The MIT License (MIT)
Project-URL: Download, https://pypi.org/project/ankiapp-easy-deck/#files
Project-URL: Source, https://github.com/johannes-programming/ankiapp_easy_deck
Keywords: AnkiApp,xml
Classifier: License :: OSI Approved :: MIT License
Classifier: Programming Language :: Python
Classifier: Programming Language :: Python :: 3
Requires-Python: >=3.11
License-File: LICENSE.txt
Requires-Dist: fileunity >=1.1
Requires-Dist: wonderparse >=1.4
